django_rest_framework_query_tools/__init__.py
django_rest_framework_query_tools/filters/__init__.py
django_rest_framework_query_tools/filters/url_fliter.py
django_rest_framework_query_tools-1.1.dist-info/LICENSE
django_rest_framework_query_tools-1.1.dist-info/METADATA
django_rest_framework_query_tools-1.1.dist-info/WHEEL
django_rest_framework_query_tools-1.1.dist-info/top_level.txt
django_rest_framework_query_tools-1.1.dist-info/RECORD
