Metadata-Version: 2.1
Name: django-rest-framework-query-tools
Version: 1.1
Summary: The package allows developers to enhance filtering capabilities within Django Rest Framework views by simply specifying the desired filter fields. By incorporating the URLFilter into views or adding it to the Django Rest Framework settings, the package streamlines the filtering process.
Home-page: https://github.com/joe-philip/django_rest_framework_query_tools
Author: Joe Philip
Author-email: joe.philip@hotmail.co.in
License: MIT License
Platform: UNKNOWN
Classifier: Environment :: Web Environment
Classifier: Framework :: Django
Classifier: Intended Audience :: Developers
Classifier: License :: OSI Approved :: MIT License
Classifier: Operating System :: OS Independent
Classifier: Programming Language :: Python
Classifier: Topic :: Internet :: WWW/HTTP
Classifier: Topic :: Software Development :: Libraries :: Application Frameworks
Requires-Dist: djangorestframework >=3.14.0
Requires-Dist: toml
